package_203_project/__init__.py
package_203_project/modified_broker.py
package_203_project/modified_portfolio_methods.py
package_203_project/package_203_project.py
package_203_project/stocks_function.py
package_203_project-0.3.0.dist-info/LICENSE
package_203_project-0.3.0.dist-info/METADATA
package_203_project-0.3.0.dist-info/WHEEL
package_203_project-0.3.0.dist-info/RECORD
