Metadata-Version: 2.3
Name: package_203_project
Version: 0.3.0
Summary: Package created for the Python course project
License: MIT
Author: Maelys Malichecq
Requires-Python: >=3.12,<4.0
Classifier: License :: OSI Approved :: MIT License
Classifier: Programming Language :: Python :: 3
Classifier: Programming Language :: Python :: 3.12
Classifier: Programming Language :: Python :: 3.13
